{
  "id": "MDk6TWlsZXN0b25lNTE0MjA5Mg==",
  "number": 109,
  "url": "https://github.com/AndroidDagashi/AndroidDagashi/milestone/109",
  "title": "109 2020-03-01",
  "description": "Android Studio 3.6安定版リリース、Vector Assetsの解説、Theme Overlayについて、古いOkHttpでAPI 30をターゲットにするとクラッシュする、など",
  "closedAt": "2020-03-01T10:16:46Z",
  "issues": {
    "totalCount": 10,
    "pageInfo": {
      "startCursor": "Y3Vyc29yOnYyOpLPf________5vOIfwmWQ==",
      "endCursor": "Y3Vyc29yOnYyOpLPf________BfOIi8MfA==",
      "hasPreviousPage": false,
      "hasNextPage": false
    },
    "nodes": [
      {
        "url": "https://github.com/AndroidDagashi/AndroidDagashi/issues/1275",
        "title": "Android Studio 3.6安定版リリース",
        "body": "https://android-developers.googleblog.com/2020/02/android-studio-36.html\r\n\r\nXMLプレビューの分割画面やView Bindingなどが入っています",
        "labels": {
          "nodes": [
            {
              "name": "AndroidStudio",
              "description": "",
              "color": "9BC363"
            },
            {
              "name": "reddit",
              "description": "",
              "color": "d93f0b"
            }
          ]
        },
        "comments": {
          "totalCount": 2,
          "pageInfo": {
            "startCursor": "Y3Vyc29yOnYyOpHOIz1ewQ==",
            "endCursor": "Y3Vyc29yOnYyOpHOI1lCfg==",
            "hasPreviousPage": false,
            "hasNextPage": false
          },
          "nodes": [
            {
              "body": "redditの反応はこちら\r\n\r\nhttps://www.reddit.com/r/androiddev/comments/f8vlbq/android_studio_36_stable_released/",
              "publishedAt": "2020-02-26T03:48:10Z",
              "author": {
                "login": "yshrsmz",
                "url": "https://github.com/yshrsmz",
                "avatarUrl": "https://avatars2.githubusercontent.com/u/654889?v=4"
              }
            },
            {
              "body": "さっそく3.6.1が出ています\r\nhttps://androidstudio.googleblog.com/2020/02/android-studio-361-available.html",
              "publishedAt": "2020-03-01T04:27:25Z",
              "author": {
                "login": "yshrsmz",
                "url": "https://github.com/yshrsmz",
                "avatarUrl": "https://avatars2.githubusercontent.com/u/654889?v=4"
              }
            }
          ]
        }
      },
      {
        "url": "https://github.com/AndroidDagashi/AndroidDagashi/issues/1276",
        "title": "Android Studio 4.0 Beta 1",
        "body": "https://androidstudio.googleblog.com/2020/02/android-studio-40-beta-1-available.html\r\n\r\nhttps://www.reddit.com/r/androiddev/comments/f9f0oe/android_studio_40_beta_1_available/",
        "labels": {
          "nodes": [
            {
              "name": "AndroidStudio",
              "description": "",
              "color": "9BC363"
            },
            {
              "name": "reddit",
              "description": "",
              "color": "d93f0b"
            }
          ]
        },
        "comments": {
          "totalCount": 1,
          "pageInfo": {
            "startCursor": "Y3Vyc29yOnYyOpHOIz1eMg==",
            "endCursor": "Y3Vyc29yOnYyOpHOIz1eMg==",
            "hasPreviousPage": false,
            "hasNextPage": false
          },
          "nodes": [
            {
              "body": "こちらのツリーで4.0の新機能がまとめられています\r\n\r\n<blockquote class=\"twitter-tweet\"><p lang=\"en\" dir=\"ltr\">1/16 With the release of <a href=\"https://twitter.com/hashtag/AndroidStudio?src=hash&amp;ref_src=twsrc%5Etfw\">#AndroidStudio</a> 4.0 beta 1, I think it&#39;s time for a quick recap on what&#39;s available in AS 4.0 in the Design Tools, in the spirit of the thread I wrote back in September, with the first canary of 3.6.<br><br>Spoiler alert: we added *many* more features… <a href=\"https://t.co/08z4kqb0hz\">https://t.co/08z4kqb0hz</a></p>&mdash; Nicolas Roard (@ camaelon) <a href=\"https://twitter.com/camaelon/status/1232457843783041024?ref_src=twsrc%5Etfw\">February 26, 2020</a></blockquote>\r\n\r\n",
              "publishedAt": "2020-02-26T03:47:26Z",
              "author": {
                "login": "yshrsmz",
                "url": "https://github.com/yshrsmz",
                "avatarUrl": "https://avatars2.githubusercontent.com/u/654889?v=4"
              }
            }
          ]
        }
      },
      {
        "url": "https://github.com/AndroidDagashi/AndroidDagashi/issues/1277",
        "title": "Jetpack Securityでデータ暗号化",
        "body": "https://medium.com/androiddevelopers/data-encryption-on-android-with-jetpack-security-e4cb0b2d2a9",
        "labels": {
          "nodes": []
        },
        "comments": {
          "totalCount": 0,
          "pageInfo": {
            "startCursor": null,
            "endCursor": null,
            "hasPreviousPage": false,
            "hasNextPage": false
          },
          "nodes": []
        }
      },
      {
        "url": "https://github.com/AndroidDagashi/AndroidDagashi/issues/1278",
        "title": "Vector Assetsの解説",
        "body": "https://www.youtube.com/watch?v=fgbl34me3kk\r\n\r\nXML、SVG、パフォーマンス、アニメーション、ツールなど、Vector Assetsに関することが解説されています。",
        "labels": {
          "nodes": []
        },
        "comments": {
          "totalCount": 0,
          "pageInfo": {
            "startCursor": null,
            "endCursor": null,
            "hasPreviousPage": false,
            "hasNextPage": false
          },
          "nodes": []
        }
      },
      {
        "url": "https://github.com/AndroidDagashi/AndroidDagashi/issues/1279",
        "title": "On-demand modulesのローカルでの開発とテスト",
        "body": "https://medium.com/androiddevelopers/local-development-and-testing-with-fakesplitinstallmanager-57083e1840a4\r\n\r\nFakeSplitInstallManagerとbundletoolを使ってOn-demand modulesをローカルで開発・テストする方法が紹介されてます。",
        "labels": {
          "nodes": []
        },
        "comments": {
          "totalCount": 0,
          "pageInfo": {
            "startCursor": null,
            "endCursor": null,
            "hasPreviousPage": false,
            "hasNextPage": false
          },
          "nodes": []
        }
      },
      {
        "url": "https://github.com/AndroidDagashi/AndroidDagashi/issues/1280",
        "title": "CryptoObjectとBiometricPromptをあわせて使う",
        "body": "https://medium.com/androiddevelopers/using-biometricprompt-with-cryptoobject-how-and-why-aace500ccdb7\r\n\r\n単に暗号化するだけでなく、Biometrics APIを組み合わせることでユーザの関与しないアクセスを制限し、よりセキュアにデータを管理しよう、ということのようです。",
        "labels": {
          "nodes": []
        },
        "comments": {
          "totalCount": 0,
          "pageInfo": {
            "startCursor": null,
            "endCursor": null,
            "hasPreviousPage": false,
            "hasNextPage": false
          },
          "nodes": []
        }
      },
      {
        "url": "https://github.com/AndroidDagashi/AndroidDagashi/issues/1281",
        "title": "Theme Overlayについて",
        "body": "https://medium.com/androiddevelopers/android-styling-themes-overlay-1ffd57745207\r\n\r\nAndroidのスタイルについての連載記事、今回はTheme Overlayについてです",
        "labels": {
          "nodes": []
        },
        "comments": {
          "totalCount": 0,
          "pageInfo": {
            "startCursor": null,
            "endCursor": null,
            "hasPreviousPage": false,
            "hasNextPage": false
          },
          "nodes": []
        }
      },
      {
        "url": "https://github.com/AndroidDagashi/AndroidDagashi/issues/1282",
        "title": "CameraXの解説",
        "body": "https://medium.com/androiddevelopers/whats-new-in-camerax-fb8568d6ddc\r\n\r\nCameraXでCamera APIで何を解決したかったかが説明されています。また、beta版もリリースされて、実用フェーズに入ったかなと思っています。",
        "labels": {
          "nodes": []
        },
        "comments": {
          "totalCount": 0,
          "pageInfo": {
            "startCursor": null,
            "endCursor": null,
            "hasPreviousPage": false,
            "hasNextPage": false
          },
          "nodes": []
        }
      },
      {
        "url": "https://github.com/AndroidDagashi/AndroidDagashi/issues/1283",
        "title": "KitKatとTLSv1.2",
        "body": "https://publicobject.com/2020/02/09/kitkat-and-tlsv1-2/\r\n\r\nKitKatまでだとセキュアでないとされているTLSv1.1をデフォルトでは使うことになってしまいます。KitKatをサポートするとしたらどういう対策がとれるか、簡単にまとめてあります。",
        "labels": {
          "nodes": []
        },
        "comments": {
          "totalCount": 0,
          "pageInfo": {
            "startCursor": null,
            "endCursor": null,
            "hasPreviousPage": false,
            "hasNextPage": false
          },
          "nodes": []
        }
      },
      {
        "url": "https://github.com/AndroidDagashi/AndroidDagashi/issues/1284",
        "title": "古いOkHttpでAPI 30をターゲットにするとクラッシュする",
        "body": "https://publicobject.com/2020/02/25/okhttp-restricted-apis/\r\n\r\nそのまんまですが古いOkHttpのバージョンでtagetSdkVersionを30にするとクラッシュするそうです。",
        "labels": {
          "nodes": []
        },
        "comments": {
          "totalCount": 0,
          "pageInfo": {
            "startCursor": null,
            "endCursor": null,
            "hasPreviousPage": false,
            "hasNextPage": false
          },
          "nodes": []
        }
      }
    ]
  }
}