{
  "id": "MI_kwDOB4jhdM4AmtF6",
  "number": 301,
  "url": "https://github.com/AndroidDagashi/AndroidDagashi/milestone/301",
  "title": "301 2023-11-12",
  "closedAt": "2023-11-12T10:41:31Z",
  "description": "Google Playの新しいポリシー, 実践 Jetpack Compose アニメーション, なぜ Kotlin Multiplatform が成功しないか, など",
  "issues": {
    "totalCount": 7,
    "pageInfo": {
      "startCursor": "Y3Vyc29yOnYyOpLPf________5vOdo1DGA==",
      "endCursor": "Y3Vyc29yOnYyOpLPf________UPOdpLWjA==",
      "hasPreviousPage": false,
      "hasNextPage": false
    },
    "nodes": [
      {
        "url": "https://github.com/AndroidDagashi/AndroidDagashi/issues/3006",
        "title": "Android Studio Hedgehog | 2023.1.1 RC 3",
        "body": "https://androidstudio.googleblog.com/2023/11/android-studio-hedgehog-202311-rc-3-now.html",
        "labels": {
          "nodes": [
            {
              "name": "AndroidStudio",
              "description": "",
              "color": "9BC363"
            }
          ]
        },
        "comments": {
          "totalCount": 0,
          "pageInfo": {
            "startCursor": null,
            "endCursor": null,
            "hasPreviousPage": false,
            "hasNextPage": false
          },
          "nodes": []
        }
      },
      {
        "url": "https://github.com/AndroidDagashi/AndroidDagashi/issues/3007",
        "title": "Android Studio Giraffe | 2022.3.1 Patch 3",
        "body": "https://androidstudio.googleblog.com/2023/11/android-studio-giraffe-202231-patch-3.html",
        "labels": {
          "nodes": [
            {
              "name": "AndroidStudio",
              "description": "",
              "color": "9BC363"
            }
          ]
        },
        "comments": {
          "totalCount": 0,
          "pageInfo": {
            "startCursor": null,
            "endCursor": null,
            "hasPreviousPage": false,
            "hasNextPage": false
          },
          "nodes": []
        }
      },
      {
        "url": "https://github.com/AndroidDagashi/AndroidDagashi/issues/3008",
        "title": "なぜ Kotlin Multiplatform が成功しないか",
        "body": "https://www.donnfelker.com/why-kotlin-multiplatform-wont-succeed/\r\nhttps://www.reddit.com/r/androiddev/comments/17pkzmr/why_kotlin_multiplatform_wont_succeed/",
        "labels": {
          "nodes": [
            {
              "name": "reddit",
              "description": "",
              "color": "d93f0b"
            },
            {
              "name": "Kotlin",
              "description": "",
              "color": "EC953C"
            },
            {
              "name": "X-Plat",
              "description": "",
              "color": "efd4a0"
            }
          ]
        },
        "comments": {
          "totalCount": 0,
          "pageInfo": {
            "startCursor": null,
            "endCursor": null,
            "hasPreviousPage": false,
            "hasNextPage": false
          },
          "nodes": []
        }
      },
      {
        "url": "https://github.com/AndroidDagashi/AndroidDagashi/issues/3009",
        "title": "JetBrains 製の新しいビルドツール、Amper ",
        "body": "https://blog.jetbrains.com/blog/2023/11/09/amper-improving-the-build-tooling-user-experience/\r\nhttps://www.reddit.com/r/androiddev/comments/17rcfu5/amper_improving_the_build_tooling_user_experience/\r\n\r\nビルドツールというよりは、ビルドツールの設定ツールというべきか。\r\nまだまだ experimental だそうです",
        "labels": {
          "nodes": [
            {
              "name": "reddit",
              "description": "",
              "color": "d93f0b"
            }
          ]
        },
        "comments": {
          "totalCount": 0,
          "pageInfo": {
            "startCursor": null,
            "endCursor": null,
            "hasPreviousPage": false,
            "hasNextPage": false
          },
          "nodes": []
        }
      },
      {
        "url": "https://github.com/AndroidDagashi/AndroidDagashi/issues/3010",
        "title": "Google Playの新しいポリシー",
        "body": "https://android-developers.googleblog.com/2023/11/ensuring-high-quality-apps-on-google-play.html\r\n\r\nGoogle Playの新しいポリシーが発表されています。アカウントに関する確認や、個人アカウントでのテスト要件などが追加されています。",
        "labels": {
          "nodes": []
        },
        "comments": {
          "totalCount": 0,
          "pageInfo": {
            "startCursor": null,
            "endCursor": null,
            "hasPreviousPage": false,
            "hasNextPage": false
          },
          "nodes": []
        }
      },
      {
        "url": "https://github.com/AndroidDagashi/AndroidDagashi/issues/3011",
        "title": "fleetがKMPをサポートする",
        "body": "https://blog.jetbrains.com/kotlin/2023/11/kotlin-multiplatform-tooling-in-fleet/\r\n\r\nリファクタリングや、コードジャンプなどの機能もサポートしているようです。",
        "labels": {
          "nodes": [
            {
              "name": "Kotlin",
              "description": "",
              "color": "EC953C"
            },
            {
              "name": "X-Plat",
              "description": "",
              "color": "efd4a0"
            }
          ]
        },
        "comments": {
          "totalCount": 0,
          "pageInfo": {
            "startCursor": null,
            "endCursor": null,
            "hasPreviousPage": false,
            "hasNextPage": false
          },
          "nodes": []
        }
      },
      {
        "url": "https://github.com/AndroidDagashi/AndroidDagashi/issues/3012",
        "title": "実践Jetpack Composeアニメーション",
        "body": "https://www.youtube.com/watch?v=HNSKJIQtb4c&list=PLWz5rJ2EKKc9Ty3Zl1hvMVUsXfkn93NRk&ab_channel=AndroidDevelopers\r\n\r\n様々なアニメーションの実装方法をstep by stepで解説しています。",
        "labels": {
          "nodes": [
            {
              "name": "Jetpack Compose",
              "description": "",
              "color": "006b75"
            }
          ]
        },
        "comments": {
          "totalCount": 0,
          "pageInfo": {
            "startCursor": null,
            "endCursor": null,
            "hasPreviousPage": false,
            "hasNextPage": false
          },
          "nodes": []
        }
      }
    ]
  }
}