{
  "id": "MI_kwDOB4jhdM4Ax6pU",
  "number": 382,
  "url": "https://github.com/AndroidDagashi/AndroidDagashi/milestone/382",
  "title": "382 2025-06-22",
  "closedAt": "2025-06-22T10:20:07Z",
  "description": null,
  "issues": {
    "totalCount": 4,
    "pageInfo": {
      "startCursor": "Y3Vyc29yOnYyOpLPf________5vOvLKXIw==",
      "endCursor": "Y3Vyc29yOnYyOpLPf________m_OvLLXEg==",
      "hasPreviousPage": false,
      "hasNextPage": false
    },
    "nodes": [
      {
        "url": "https://github.com/AndroidDagashi/AndroidDagashi/issues/3471",
        "title": "Now in Android 118",
        "body": "https://medium.com/androiddevelopers/now-in-android-118-google-i-o-2025-part-ii-0176766c2061\n\nGoogle I/O 2025の話題を中心にまとめられています。",
        "labels": {
          "nodes": []
        },
        "comments": {
          "totalCount": 0,
          "pageInfo": {
            "startCursor": null,
            "endCursor": null,
            "hasPreviousPage": false,
            "hasNextPage": false
          },
          "nodes": []
        }
      },
      {
        "url": "https://github.com/AndroidDagashi/AndroidDagashi/issues/3472",
        "title": "KotlinConf 2025の動画",
        "body": "https://kotlinconf.com/talks/\n",
        "labels": {
          "nodes": [
            {
              "name": "Kotlin",
              "description": "",
              "color": "EC953C"
            }
          ]
        },
        "comments": {
          "totalCount": 0,
          "pageInfo": {
            "startCursor": null,
            "endCursor": null,
            "hasPreviousPage": false,
            "hasNextPage": false
          },
          "nodes": []
        }
      },
      {
        "url": "https://github.com/AndroidDagashi/AndroidDagashi/issues/3473",
        "title": "Ktor3.2.0のリリース",
        "body": "https://blog.jetbrains.com/kotlin/2025/06/ktor-3-2-0-is-now-available/\n",
        "labels": {
          "nodes": []
        },
        "comments": {
          "totalCount": 0,
          "pageInfo": {
            "startCursor": null,
            "endCursor": null,
            "hasPreviousPage": false,
            "hasNextPage": false
          },
          "nodes": []
        }
      },
      {
        "url": "https://github.com/AndroidDagashi/AndroidDagashi/issues/3474",
        "title": "Jetpack Composeのアニメーションの作り方",
        "body": "https://proandroiddev.com/article-4-animations-in-jetpack-compose-from-state-to-smooth-transitions-eb5a5076fd25\n\nStateを中心に、Jetpack Composeのアニメーションの作成の仕方を解説をしています。",
        "labels": {
          "nodes": []
        },
        "comments": {
          "totalCount": 0,
          "pageInfo": {
            "startCursor": null,
            "endCursor": null,
            "hasPreviousPage": false,
            "hasNextPage": false
          },
          "nodes": []
        }
      }
    ]
  }
}